paimon_python_api/__init__.py
paimon_python_api/catalog.py
paimon_python_api/commit_message.py
paimon_python_api/read_builder.py
paimon_python_api/split.py
paimon_python_api/table.py
paimon_python_api/table_commit.py
paimon_python_api/table_read.py
paimon_python_api/table_scan.py
paimon_python_api/table_write.py
paimon_python_api/write_builder.py
paimon_python_java/__init__.py
paimon_python_java/gateway_server.py
paimon_python_java/java_gateway.py
paimon_python_java/pypaimon.py
paimon_python_java/java_dependencies/paimon-python-java-bridge.jar
paimon_python_java/util/__init__.py
paimon_python_java/util/constants.py
paimon_python_java/util/exceptions.py
paimon_python_java/util/java_utils.py
paimon_python_ali-0.1.1.dist-info/LICENSE
paimon_python_ali-0.1.1.dist-info/METADATA
paimon_python_ali-0.1.1.dist-info/NOTICE
paimon_python_ali-0.1.1.dist-info/WHEEL
paimon_python_ali-0.1.1.dist-info/top_level.txt
paimon_python_ali-0.1.1.dist-info/RECORD
